{"data":{"site":{"siteMetadata":{"title":"Sean McPherson","author":"Sean McPherson"}},"allMarkdownRemark":{"edges":[{"node":{"excerpt":"After deciding to transition away from Medium and  launch my own blog , the next decision to make was selecting a publishing platform. I…","fields":{"slug":"/why-gatsby/"},"frontmatter":{"category":"meta","date":"December 4, 2018","summary":false,"tags":["blogging","gatsby"],"title":"Why Gatsby?"}}},{"node":{"excerpt":"For over a year and half I have been happily blogging on Medium. I was quick to sign up when the platform first launched (and snag that…","fields":{"slug":"/why-a-blog/"},"frontmatter":{"category":"meta","date":"December 4, 2018","summary":false,"tags":["blogging","medium"],"title":"Why a blog?"}}}]}},"pageContext":{"category":"meta"}}